ml_project_setup/__init__.py
ml_project_setup/ml_project_setup.py
ml_project_setup-0.4.dist-info/LICENSE
ml_project_setup-0.4.dist-info/METADATA
ml_project_setup-0.4.dist-info/WHEEL
ml_project_setup-0.4.dist-info/entry_points.txt
ml_project_setup-0.4.dist-info/top_level.txt
ml_project_setup-0.4.dist-info/RECORD
